zc.queue-2.0.0-py3.5-nspkg.pth
zc/queue/__init__.py
zc/queue/_queue.py
zc/queue/interfaces.py
zc/queue/queue.rst
zc/queue/tests.py
zc.queue-2.0.0.dist-info/DESCRIPTION.rst
zc.queue-2.0.0.dist-info/METADATA
zc.queue-2.0.0.dist-info/RECORD
zc.queue-2.0.0.dist-info/WHEEL
zc.queue-2.0.0.dist-info/metadata.json
zc.queue-2.0.0.dist-info/namespace_packages.txt
zc.queue-2.0.0.dist-info/top_level.txt
