Metadata-Version: 2.0
Name: zc.queue
Version: 2.0.0
Summary: Queues that are optimized for persistency via the ZODB.
Requires-Dist: ZODB
Requires-Dist: persistent
Requires-Dist: setuptools
Requires-Dist: zope.interface
Provides-Extra: test
Requires-Dist: zope.testing; extra == 'test'
Requires-Dist: zope.testrunner; extra == 'test'
